cf_pipelines/__init__.py
cf_pipelines/base/__init__.py
cf_pipelines/base/helper_classes.py
cf_pipelines/base/pipeline.py
cf_pipelines/base/utils.py
code_first_pipelines-1.0.0.dist-info/entry_points.txt
code_first_pipelines-1.0.0.dist-info/WHEEL
code_first_pipelines-1.0.0.dist-info/METADATA
code_first_pipelines-1.0.0.dist-info/RECORD
