Metadata-Version: 2.1
Name: code-first-pipelines
Version: 1.0.0
Summary: A framework built on top of Ploomber that allows code-first definition of pipelines.
Author: Prediction and Learning at Simply Business
Author-email: pal@simplybusiness.co.uk
Requires-Python: >=3.8,<3.12
Classifier: Programming Language :: Python :: 3
Classifier: Programming Language :: Python :: 3.10
Classifier: Programming Language :: Python :: 3.8
Classifier: Programming Language :: Python :: 3.9
Provides-Extra: graphviz
Requires-Dist: cookiecutter (>=2.1.1,<3.0.0)
Requires-Dist: mlflow (>=1.29.0,<2.0.0)
Requires-Dist: ploomber (>=0.21.1,<0.22.0)
Requires-Dist: pygraphviz (>=1.10,<2.0); extra == "graphviz"
Requires-Dist: typer (>=0.6.1,<0.7.0)
